LICENSE
README.md
setup.py
nanoCEM/CE_magnifier_test.py
nanoCEM/__init__.py
nanoCEM/alignment_magnifier
nanoCEM/cem_utils.py
nanoCEM/current_events_magnifier
nanoCEM/extract_sub_fast5_from_bam
nanoCEM/machine_learning_trainer.py
nanoCEM/normalization.py
nanoCEM/plot.py
nanoCEM/read_f5c_eventalign.py
nanoCEM/read_f5c_resquiggle.py
nanoCEM/read_move_table.py
nanoCEM/read_tombo_resquiggle.py
nanoCEM.egg-info/PKG-INFO
nanoCEM.egg-info/SOURCES.txt
nanoCEM.egg-info/dependency_links.txt
nanoCEM.egg-info/requires.txt
nanoCEM.egg-info/top_level.txt