Metadata-Version: 2.1
Name: nanoCEM
Version: 0.0.5.9
Summary: A simple tool designed to visualize the features that distinguish between two groups of ONT data at the site level.                It supports 4 re-squiggle program(tombo resquiggle/f5c resquiggle/f5c eventalign/move_table).
Home-page: https://github.com/lrslab/nanoCEM
Author: GUO Zhihao
Author-email: qhuozhihao@icloud.com
Classifier: Programming Language :: Python :: 3
Classifier: License :: OSI Approved :: MIT License
Classifier: Operating System :: OS Independent
Requires-Python: >=3.7.0,<=3.11.7
License-File: LICENSE
Requires-Dist: h5py>=3.8.0
Requires-Dist: numpy>=1.23.0
Requires-Dist: pandas>=1.5.0
Requires-Dist: plotnine==0.12.4
Requires-Dist: tqdm>=4.62.0
Requires-Dist: pysam>=0.21.0
Requires-Dist: pyslow5>=1.0.0
Requires-Dist: vbz_h5py_plugin>=1.0.1
Requires-Dist: biopython>=1.80
Requires-Dist: scikit-learn>=1.2.2
Requires-Dist: squigualiser==0.5.1
